{"id":"LUCYHFQ660RJY","name":"Pinterest","size":49875,"btime":1711734430686,"mtime":1711734431126,"ext":"jpg","tags":["egirl+eboy"],"folders":["LUCYEYMCMWXGE"],"isDeleted":false,"url":"https://www.pinterest.ca/pin/742531057297611800/","annotation":"","modificationTime":1711734314052,"height":539,"width":540,"noThumbnail":true,"palettes":[{"color":[170,169,167],"ratio":57},{"color":[63,65,71],"ratio":16},{"color":[106,108,111],"ratio":14},{"color":[136,136,134],"ratio":5},{"color":[138,119,117],"ratio":2.34},{"color":[191,192,189],"ratio":1.51},{"color":[84,92,96],"ratio":1.1},{"color":[153,138,133],"ratio":0.93}],"lastModified":1711734656215}