{"id":"LUCZ0R294NHAW","name":"Pinterest","size":116683,"btime":1711735331843,"mtime":1711735332610,"ext":"jpg","tags":["roadmen"],"folders":["LUCZ0MWGNYLQU"],"isDeleted":false,"url":"https://www.pinterest.com/pin/1043287069901789576/","annotation":"","modificationTime":1711735326306,"height":640,"width":638,"noThumbnail":true,"palettes":[{"color":[115,102,89],"ratio":40},{"color":[26,26,23],"ratio":25},{"color":[199,181,152],"ratio":9},{"color":[65,64,61],"ratio":9},{"color":[157,144,124],"ratio":7},{"color":[155,155,145],"ratio":4.06},{"color":[75,38,34],"ratio":1.39},{"color":[167,175,160],"ratio":1.37},{"color":[73,60,33],"ratio":0.96}],"lastModified":1711735337782}