{"id":"LUCYEZ3KXD7JZ","name":"Pinterest","size":416449,"btime":1711734315826,"mtime":1711734316399,"ext":"jpg","tags":["egirl+eboy"],"folders":["LUCYEYMCMWXGE"],"isDeleted":false,"url":"https://www.pinterest.ca/pin/742531057340665332/","annotation":"","modificationTime":1711734315156,"height":2048,"width":1194,"palettes":[{"color":[171,154,221],"ratio":27},{"color":[49,44,63],"ratio":16},{"color":[237,231,248],"ratio":13},{"color":[111,94,178],"ratio":9},{"color":[163,105,204],"ratio":9},{"color":[210,204,232],"ratio":7},{"color":[87,83,94],"ratio":5},{"color":[236,191,224],"ratio":4.69},{"color":[100,60,118],"ratio":4.57},{"color":[152,135,156],"ratio":1.72}],"lastModified":1711734654467}