{"id":"LUCYHONLXY8X2","name":"Pinterest","size":438723,"btime":1711734442258,"mtime":1711734442932,"ext":"jpg","tags":["egirl+eboy"],"folders":["LUCYEYMCMWXGE"],"isDeleted":false,"url":"https://www.pinterest.ca/pin/742531057297333453/","annotation":"","modificationTime":1711734313925,"height":1200,"width":1200,"noThumbnail":true,"palettes":[{"color":[92,92,90],"ratio":55},{"color":[190,167,169],"ratio":26},{"color":[159,123,124],"ratio":11},{"color":[118,130,178],"ratio":2.32},{"color":[123,136,125],"ratio":1.44},{"color":[143,181,183],"ratio":1.25},{"color":[191,137,72],"ratio":0.51},{"color":[41,46,53],"ratio":0.36}],"lastModified":1711734656611}