{"id":"LUCZ0P9YV55MW","name":"Pinterest","size":179967,"btime":1711735329528,"mtime":1711735329914,"ext":"jpg","tags":["roadmen"],"folders":["LUCZ0MWGNYLQU"],"isDeleted":false,"url":"https://www.pinterest.com/pin/1043287069901789600/","annotation":"","modificationTime":1711735326332,"height":928,"width":750,"noThumbnail":true,"palettes":[{"color":[35,34,30],"ratio":39},{"color":[144,146,98],"ratio":18},{"color":[117,123,85],"ratio":12},{"color":[201,197,117],"ratio":8},{"color":[100,96,69],"ratio":7},{"color":[78,81,70],"ratio":6},{"color":[167,174,120],"ratio":3.18},{"color":[67,67,68],"ratio":2.25},{"color":[101,104,102],"ratio":1.52}],"lastModified":1711735337774}