{"id":"LUCYVIQYQTEWU","name":"GIF","size":185796,"btime":1711735087793,"mtime":1711735088163,"ext":"gif","tags":["mix (anime + irl)"],"folders":["LUCYVET8HY2YJ"],"isDeleted":false,"url":"https://www.pinterest.com/pin/704180091759091266/","annotation":"","modificationTime":1711735082545,"height":250,"width":500,"palettes":[{"color":[78,71,117],"ratio":72},{"color":[46,41,70],"ratio":9},{"color":[19,16,32],"ratio":7},{"color":[104,99,156],"ratio":5},{"color":[230,229,237],"ratio":3.41},{"color":[135,126,148],"ratio":0.9},{"color":[37,28,65],"ratio":0.69},{"color":[147,143,194],"ratio":0.36}],"lastModified":1711735137473}