{"id":"LUCY3W50QJAZT","name":"Pinterest","size":63584,"btime":1711733798776,"mtime":1711733799173,"ext":"jpg","tags":["Softly"],"folders":["LUCY3RGPEVZN5"],"isDeleted":false,"url":"https://www.pinterest.com/pin/635429828685714410/","annotation":"","modificationTime":1711733792627,"height":750,"width":750,"noThumbnail":true,"palettes":[{"color":[118,129,142],"ratio":44},{"color":[192,224,242],"ratio":14},{"color":[141,166,186],"ratio":10},{"color":[167,198,219],"ratio":7},{"color":[104,90,87],"ratio":6},{"color":[180,200,219],"ratio":5},{"color":[156,184,199],"ratio":4.48},{"color":[104,90,112],"ratio":2.18},{"color":[149,144,153],"ratio":1.94},{"color":[79,113,131],"ratio":1.84}],"lastModified":1711733817693}