{"id":"LUCYW74ULRZ5I","name":"GIF","size":2007279,"btime":1711735119391,"mtime":1711735119798,"ext":"gif","tags":["mix (anime + irl)"],"folders":["LUCYVET8HY2YJ"],"isDeleted":false,"url":"https://www.pinterest.com/pin/704180091749734358/","annotation":"","modificationTime":1711735082371,"height":281,"width":500,"palettes":[{"color":[9,9,15],"ratio":62},{"color":[84,56,44],"ratio":20},{"color":[33,48,54],"ratio":5},{"color":[54,85,91],"ratio":4.46},{"color":[42,25,20],"ratio":3.88},{"color":[33,37,33],"ratio":1.35},{"color":[106,153,154],"ratio":0.84},{"color":[55,68,64],"ratio":0.8}],"lastModified":1711735137522}