{"id":"LUCZ0NWG7P1VF","name":"Pinterest","size":55271,"btime":1711735327746,"mtime":1711735327761,"ext":"jpg","tags":["roadmen"],"folders":["LUCZ0MWGNYLQU"],"isDeleted":false,"url":"https://www.pinterest.com/pin/1043287069901789653/","annotation":"","modificationTime":1711735326368,"height":503,"width":750,"noThumbnail":true,"palettes":[{"color":[31,28,37],"ratio":48},{"color":[73,70,93],"ratio":23},{"color":[66,65,70],"ratio":7},{"color":[98,95,126],"ratio":6},{"color":[159,156,183],"ratio":5},{"color":[98,95,99],"ratio":4.06},{"color":[60,51,56],"ratio":2.01},{"color":[92,83,96],"ratio":1.63}],"lastModified":1711735337749}