{"id":"LUCYHKQNY0VA6","name":"Pinterest","size":33435,"btime":1711734437184,"mtime":1711734437622,"ext":"jpg","tags":["egirl+eboy"],"folders":["LUCYEYMCMWXGE"],"isDeleted":false,"url":"https://www.pinterest.ca/pin/742531057297355293/","annotation":"","modificationTime":1711734313983,"height":540,"width":540,"noThumbnail":true,"palettes":[{"color":[8,22,28],"ratio":51},{"color":[18,92,124],"ratio":23},{"color":[162,154,147],"ratio":9},{"color":[18,57,79],"ratio":3.82},{"color":[29,52,61],"ratio":3.56},{"color":[119,102,92],"ratio":3.15},{"color":[45,83,99],"ratio":3.04},{"color":[56,59,60],"ratio":1.8}],"lastModified":1711734656362}