{"id":"LUCYH4PCDJXR4","name":"Pinterest","size":41811,"btime":1711734416400,"mtime":1711734416823,"ext":"jpg","tags":["egirl+eboy"],"folders":["LUCYEYMCMWXGE"],"isDeleted":false,"url":"https://www.pinterest.ca/pin/742531057297825994/","annotation":"","modificationTime":1711734314208,"height":777,"width":677,"noThumbnail":true,"palettes":[{"color":[244,243,204],"ratio":66},{"color":[107,93,42],"ratio":21},{"color":[225,178,117],"ratio":4.67},{"color":[210,121,65],"ratio":3.32},{"color":[163,106,50],"ratio":2.37},{"color":[236,208,156],"ratio":1.17},{"color":[211,118,103],"ratio":0.44}],"lastModified":1711734655865}