{"id":"LUCYW1O4J9UC4","name":"GIF","size":1570236,"btime":1711735112309,"mtime":1711735113219,"ext":"gif","tags":["mix (anime + irl)"],"folders":["LUCYVET8HY2YJ"],"isDeleted":false,"url":"https://www.pinterest.com/pin/704180091750331990/","annotation":"","modificationTime":1711735082409,"height":304,"width":540,"palettes":[{"color":[156,118,151],"ratio":36},{"color":[50,47,66],"ratio":22},{"color":[230,112,176],"ratio":12},{"color":[86,86,119],"ratio":9},{"color":[221,204,246],"ratio":6},{"color":[157,65,103],"ratio":5},{"color":[124,32,62],"ratio":2.64},{"color":[163,33,83],"ratio":2.15},{"color":[174,159,213],"ratio":1.4},{"color":[136,90,102],"ratio":0.65}],"lastModified":1711735137514}