{"id":"LUCYH8VPZMU3H","name":"Pinterest","size":78120,"btime":1711734421814,"mtime":1711734422345,"ext":"jpg","tags":["egirl+eboy"],"folders":["LUCYEYMCMWXGE"],"isDeleted":false,"url":"https://www.pinterest.ca/pin/742531057297825762/","annotation":"","modificationTime":1711734314147,"height":1200,"width":848,"noThumbnail":true,"palettes":[{"color":[33,33,38],"ratio":52},{"color":[249,244,236],"ratio":30},{"color":[123,180,179],"ratio":11},{"color":[196,169,152],"ratio":2.18},{"color":[194,56,34],"ratio":1.41},{"color":[123,109,99],"ratio":1.09},{"color":[79,115,111],"ratio":0.31}],"lastModified":1711734656079}