{"id":"LUCYHGJMEFEO6","name":"Pinterest","size":68052,"btime":1711734431746,"mtime":1711734432206,"ext":"jpg","tags":["egirl+eboy"],"folders":["LUCYEYMCMWXGE"],"isDeleted":false,"url":"https://www.pinterest.ca/pin/742531057297611772/","annotation":"","modificationTime":1711734314038,"height":720,"width":720,"noThumbnail":true,"palettes":[{"color":[34,51,59],"ratio":53},{"color":[214,205,206],"ratio":29},{"color":[51,101,132],"ratio":8},{"color":[127,142,161],"ratio":3.5},{"color":[107,118,128],"ratio":2.78},{"color":[177,155,146],"ratio":1.64},{"color":[148,156,175],"ratio":0.31}],"lastModified":1711734656254}