{"id":"LUCYHEOG6286Z","name":"Pinterest","size":9432,"btime":1711734429328,"mtime":1711734429630,"ext":"jpg","tags":["egirl+eboy"],"folders":["LUCYEYMCMWXGE"],"isDeleted":false,"url":"https://www.pinterest.ca/pin/742531057297611822/","annotation":"","modificationTime":1711734314061,"height":296,"width":256,"noThumbnail":true,"palettes":[{"color":[89,91,97],"ratio":70},{"color":[179,177,186],"ratio":12},{"color":[23,23,30],"ratio":9},{"color":[146,150,164],"ratio":3.67},{"color":[184,169,169],"ratio":1.99},{"color":[45,44,52],"ratio":0.8},{"color":[157,164,171],"ratio":0.32}],"lastModified":1711734656212}